{
	"format_version": "1.8.0",
	"minecraft:spawn_rules": {
		"description": {
			"identifier": "borgy:poison_headcrab",
			"population_control": "monster"
		},
		"conditions": [
			{
				"minecraft:spawns_underground": {},
				"minecraft:weight": {
					"default": 15
				},
				"minecraft:biome_filter": {
					"any_of": [
						{
							"test": "has_biome_tag",
							"operator": "==",
							"value": "monster"
						}
					]
				},
				"minecraft:density_limit": {
					"surface": 8
				},
				"minecraft:height_filter": {
				  "min": -63,
				  "max": 63
				}
			}
		]
	}
}